{
  "id": "00000000-0000-0000-0000-000000000000",
  "prevId": "",
  "version": "1",
  "dialect": "singlestore",
  "tables": {
    "account": {
      "name": "account",
      "columns": {
        "id": {
          "autoincrement": false,
          "name": "id",
          "type": "varchar(36)",
          "primaryKey": false,
          "notNull": true
        },
        "provider_id": {
          "autoincrement": false,
          "name": "provider_id",
          "type": "text",
          "primaryKey": false,
          "notNull": true
        },
        "account_id": {
          "autoincrement": false,
          "name": "account_id",
          "type": "text",
          "primaryKey": false,
          "notNull": true
        },
        "user_id": {
          "autoincrement": false,
          "name": "user_id",
          "type": "varchar(36)",
          "primaryKey": false,
          "notNull": true
        },
        "access_token": {
          "autoincrement": false,
          "name": "access_token",
          "type": "text",
          "primaryKey": false,
          "notNull": false
        },
        "refresh_token": {
          "autoincrement": false,
          "name": "refresh_token",
          "type": "text",
          "primaryKey": false,
          "notNull": false
        },
        "id_token": {
          "autoincrement": false,
          "name": "id_token",
          "type": "text",
          "primaryKey": false,
          "notNull": false
        },
        "access_token_expires_at": {
          "autoincrement": false,
          "name": "access_token_expires_at",
          "type": "timestamp",
          "primaryKey": false,
          "notNull": false
        },
        "refresh_token_expires_at": {
          "autoincrement": false,
          "name": "refresh_token_expires_at",
          "type": "timestamp",
          "primaryKey": false,
          "notNull": false
        },
        "scope": {
          "autoincrement": false,
          "name": "scope",
          "type": "text",
          "primaryKey": false,
          "notNull": false
        },
        "created_at": {
          "default": "CURRENT_TIMESTAMP",
          "autoincrement": false,
          "name": "created_at",
          "type": "timestamp",
          "primaryKey": false,
          "notNull": true
        },
        "updated_at": {
          "default": "CURRENT_TIMESTAMP",
          "autoincrement": false,
          "name": "updated_at",
          "type": "timestamp",
          "primaryKey": false,
          "notNull": true,
          "onUpdate": true
        },
        "password": {
          "autoincrement": false,
          "name": "password",
          "type": "text",
          "primaryKey": false,
          "notNull": false
        }
      },
      "compositePrimaryKeys": {
        "account_id": {
          "name": "account_id",
          "columns": [
            "id"
          ]
        }
      },
      "indexes": {},
      "uniqueConstraints": {}
    },
    "accounts": {
      "name": "accounts",
      "columns": {
        "account_id": {
          "autoincrement": true,
          "name": "account_id",
          "type": "bigint",
          "primaryKey": false,
          "notNull": true
        },
        "name": {
          "autoincrement": false,
          "name": "name",
          "type": "varchar(255)",
          "primaryKey": false,
          "notNull": true
        },
        "logo": {
          "autoincrement": false,
          "name": "logo",
          "type": "varchar(2048)",
          "primaryKey": false,
          "notNull": false
        },
        "address": {
          "autoincrement": false,
          "name": "address",
          "type": "varchar(500)",
          "primaryKey": false,
          "notNull": false
        },
        "phone": {
          "autoincrement": false,
          "name": "phone",
          "type": "varchar(20)",
          "primaryKey": false,
          "notNull": false
        },
        "email": {
          "autoincrement": false,
          "name": "email",
          "type": "varchar(255)",
          "primaryKey": false,
          "notNull": false
        },
        "website": {
          "autoincrement": false,
          "name": "website",
          "type": "varchar(255)",
          "primaryKey": false,
          "notNull": false
        },
        "portal_settings": {
          "default": "'{}'",
          "autoincrement": false,
          "name": "portal_settings",
          "type": "JSON",
          "primaryKey": false,
          "notNull": false
        },
        "payment_settings": {
          "default": "'{}'",
          "autoincrement": false,
          "name": "payment_settings",
          "type": "JSON",
          "primaryKey": false,
          "notNull": false
        },
        "preferences": {
          "default": "'{}'",
          "autoincrement": false,
          "name": "preferences",
          "type": "JSON",
          "primaryKey": false,
          "notNull": false
        },
        "plan": {
          "default": "'basic'",
          "autoincrement": false,
          "name": "plan",
          "type": "varchar(50)",
          "primaryKey": false,
          "notNull": false
        },
        "subscription_status": {
          "default": "'active'",
          "autoincrement": false,
          "name": "subscription_status",
          "type": "varchar(20)",
          "primaryKey": false,
          "notNull": false
        },
        "created_at": {
          "default": "CURRENT_TIMESTAMP",
          "autoincrement": false,
          "name": "created_at",
          "type": "timestamp",
          "primaryKey": false,
          "notNull": true
        },
        "updated_at": {
          "default": "CURRENT_TIMESTAMP",
          "autoincrement": false,
          "name": "updated_at",
          "type": "timestamp",
          "primaryKey": false,
          "notNull": true,
          "onUpdate": true
        },
        "is_active": {
          "default": 1,
          "autoincrement": false,
          "name": "is_active",
          "type": "tinyint",
          "primaryKey": false,
          "notNull": false
        }
      },
      "compositePrimaryKeys": {
        "accounts_account_id": {
          "name": "accounts_account_id",
          "columns": [
            "account_id"
          ]
        }
      },
      "indexes": {},
      "uniqueConstraints": {}
    },
    "appointments": {
      "name": "appointments",
      "columns": {
        "appointment_id": {
          "autoincrement": true,
          "name": "appointment_id",
          "type": "bigint",
          "primaryKey": false,
          "notNull": true
        },
        "user_id": {
          "autoincrement": false,
          "name": "user_id",
          "type": "varchar(36)",
          "primaryKey": false,
          "notNull": true
        },
        "contact_id": {
          "autoincrement": false,
          "name": "contact_id",
          "type": "bigint",
          "primaryKey": false,
          "notNull": true
        },
        "listing_id": {
          "autoincrement": false,
          "name": "listing_id",
          "type": "bigint",
          "primaryKey": false,
          "notNull": false
        },
        "lead_id": {
          "autoincrement": false,
          "name": "lead_id",
          "type": "bigint",
          "primaryKey": false,
          "notNull": false
        },
        "deal_id": {
          "autoincrement": false,
          "name": "deal_id",
          "type": "bigint",
          "primaryKey": false,
          "notNull": false
        },
        "prospect_id": {
          "autoincrement": false,
          "name": "prospect_id",
          "type": "bigint",
          "primaryKey": false,
          "notNull": false
        },
        "datetime_start": {
          "autoincrement": false,
          "name": "datetime_start",
          "type": "timestamp",
          "primaryKey": false,
          "notNull": true
        },
        "datetime_end": {
          "autoincrement": false,
          "name": "datetime_end",
          "type": "timestamp",
          "primaryKey": false,
          "notNull": true
        },
        "status": {
          "default": "'Scheduled'",
          "autoincrement": false,
          "name": "status",
          "type": "varchar(20)",
          "primaryKey": false,
          "notNull": true
        },
        "notes": {
          "autoincrement": false,
          "name": "notes",
          "type": "text",
          "primaryKey": false,
          "notNull": false
        },
        "is_active": {
          "default": 1,
          "autoincrement": false,
          "name": "is_active",
          "type": "tinyint",
          "primaryKey": false,
          "notNull": false
        },
        "created_at": {
          "default": "CURRENT_TIMESTAMP",
          "autoincrement": false,
          "name": "created_at",
          "type": "timestamp",
          "primaryKey": false,
          "notNull": true
        },
        "updated_at": {
          "default": "CURRENT_TIMESTAMP",
          "autoincrement": false,
          "name": "updated_at",
          "type": "timestamp",
          "primaryKey": false,
          "notNull": true,
          "onUpdate": true
        }
      },
      "compositePrimaryKeys": {
        "appointments_appointment_id": {
          "name": "appointments_appointment_id",
          "columns": [
            "appointment_id"
          ]
        }
      },
      "indexes": {},
      "uniqueConstraints": {}
    },
    "contacts": {
      "name": "contacts",
      "columns": {
        "contact_id": {
          "autoincrement": true,
          "name": "contact_id",
          "type": "bigint",
          "primaryKey": false,
          "notNull": true
        },
        "account_id": {
          "autoincrement": false,
          "name": "account_id",
          "type": "bigint",
          "primaryKey": false,
          "notNull": true
        },
        "first_name": {
          "autoincrement": false,
          "name": "first_name",
          "type": "varchar(100)",
          "primaryKey": false,
          "notNull": true
        },
        "last_name": {
          "autoincrement": false,
          "name": "last_name",
          "type": "varchar(100)",
          "primaryKey": false,
          "notNull": true
        },
        "email": {
          "autoincrement": false,
          "name": "email",
          "type": "varchar(255)",
          "primaryKey": false,
          "notNull": false
        },
        "phone": {
          "autoincrement": false,
          "name": "phone",
          "type": "varchar(20)",
          "primaryKey": false,
          "notNull": false
        },
        "additional_info": {
          "default": "'{}'",
          "autoincrement": false,
          "name": "additional_info",
          "type": "JSON",
          "primaryKey": false,
          "notNull": false
        },
        "org_id": {
          "autoincrement": false,
          "name": "org_id",
          "type": "bigint",
          "primaryKey": false,
          "notNull": false
        },
        "is_active": {
          "default": 1,
          "autoincrement": false,
          "name": "is_active",
          "type": "tinyint",
          "primaryKey": false,
          "notNull": false
        },
        "created_at": {
          "default": "CURRENT_TIMESTAMP",
          "autoincrement": false,
          "name": "created_at",
          "type": "timestamp",
          "primaryKey": false,
          "notNull": true
        },
        "updated_at": {
          "default": "CURRENT_TIMESTAMP",
          "autoincrement": false,
          "name": "updated_at",
          "type": "timestamp",
          "primaryKey": false,
          "notNull": true,
          "onUpdate": true
        }
      },
      "compositePrimaryKeys": {
        "contacts_contact_id": {
          "name": "contacts_contact_id",
          "columns": [
            "contact_id"
          ]
        }
      },
      "indexes": {},
      "uniqueConstraints": {}
    },
    "deal_participants": {
      "name": "deal_participants",
      "columns": {
        "deal_id": {
          "autoincrement": false,
          "name": "deal_id",
          "type": "bigint",
          "primaryKey": false,
          "notNull": true
        },
        "contact_id": {
          "autoincrement": false,
          "name": "contact_id",
          "type": "bigint",
          "primaryKey": false,
          "notNull": true
        },
        "role": {
          "autoincrement": false,
          "name": "role",
          "type": "varchar(50)",
          "primaryKey": false,
          "notNull": true
        }
      },
      "compositePrimaryKeys": {},
      "indexes": {},
      "uniqueConstraints": {}
    },
    "deals": {
      "name": "deals",
      "columns": {
        "deal_id": {
          "autoincrement": true,
          "name": "deal_id",
          "type": "bigint",
          "primaryKey": false,
          "notNull": true
        },
        "listing_id": {
          "autoincrement": false,
          "name": "listing_id",
          "type": "bigint",
          "primaryKey": false,
          "notNull": true
        },
        "stage": {
          "autoincrement": false,
          "name": "stage",
          "type": "varchar(20)",
          "primaryKey": false,
          "notNull": true
        },
        "close_date": {
          "autoincrement": false,
          "name": "close_date",
          "type": "timestamp",
          "primaryKey": false,
          "notNull": false
        },
        "created_at": {
          "default": "CURRENT_TIMESTAMP",
          "autoincrement": false,
          "name": "created_at",
          "type": "timestamp",
          "primaryKey": false,
          "notNull": true
        },
        "updated_at": {
          "default": "CURRENT_TIMESTAMP",
          "autoincrement": false,
          "name": "updated_at",
          "type": "timestamp",
          "primaryKey": false,
          "notNull": true,
          "onUpdate": true
        }
      },
      "compositePrimaryKeys": {
        "deals_deal_id": {
          "name": "deals_deal_id",
          "columns": [
            "deal_id"
          ]
        }
      },
      "indexes": {},
      "uniqueConstraints": {}
    },
    "documents": {
      "name": "documents",
      "columns": {
        "doc_id": {
          "autoincrement": true,
          "name": "doc_id",
          "type": "bigint",
          "primaryKey": false,
          "notNull": true
        },
        "filename": {
          "autoincrement": false,
          "name": "filename",
          "type": "varchar(255)",
          "primaryKey": false,
          "notNull": true
        },
        "file_type": {
          "autoincrement": false,
          "name": "file_type",
          "type": "varchar(50)",
          "primaryKey": false,
          "notNull": true
        },
        "file_url": {
          "autoincrement": false,
          "name": "file_url",
          "type": "varchar(2048)",
          "primaryKey": false,
          "notNull": true
        },
        "user_id": {
          "autoincrement": false,
          "name": "user_id",
          "type": "varchar(36)",
          "primaryKey": false,
          "notNull": true
        },
        "property_id": {
          "autoincrement": false,
          "name": "property_id",
          "type": "bigint",
          "primaryKey": false,
          "notNull": false
        },
        "contact_id": {
          "autoincrement": false,
          "name": "contact_id",
          "type": "bigint",
          "primaryKey": false,
          "notNull": false
        },
        "listing_id": {
          "autoincrement": false,
          "name": "listing_id",
          "type": "bigint",
          "primaryKey": false,
          "notNull": false
        },
        "lead_id": {
          "autoincrement": false,
          "name": "lead_id",
          "type": "bigint",
          "primaryKey": false,
          "notNull": false
        },
        "deal_id": {
          "autoincrement": false,
          "name": "deal_id",
          "type": "bigint",
          "primaryKey": false,
          "notNull": false
        },
        "appointment_id": {
          "autoincrement": false,
          "name": "appointment_id",
          "type": "bigint",
          "primaryKey": false,
          "notNull": false
        },
        "prospect_id": {
          "autoincrement": false,
          "name": "prospect_id",
          "type": "bigint",
          "primaryKey": false,
          "notNull": false
        },
        "document_key": {
          "autoincrement": false,
          "name": "document_key",
          "type": "varchar(2048)",
          "primaryKey": false,
          "notNull": true
        },
        "s3key": {
          "autoincrement": false,
          "name": "s3key",
          "type": "varchar(2048)",
          "primaryKey": false,
          "notNull": true
        },
        "document_tag": {
          "autoincrement": false,
          "name": "document_tag",
          "type": "varchar(255)",
          "primaryKey": false,
          "notNull": false
        },
        "document_order": {
          "default": 0,
          "autoincrement": false,
          "name": "document_order",
          "type": "int",
          "primaryKey": false,
          "notNull": true
        },
        "uploaded_at": {
          "default": "CURRENT_TIMESTAMP",
          "autoincrement": false,
          "name": "uploaded_at",
          "type": "timestamp",
          "primaryKey": false,
          "notNull": true
        },
        "is_active": {
          "default": 1,
          "autoincrement": false,
          "name": "is_active",
          "type": "tinyint",
          "primaryKey": false,
          "notNull": false
        },
        "created_at": {
          "default": "CURRENT_TIMESTAMP",
          "autoincrement": false,
          "name": "created_at",
          "type": "timestamp",
          "primaryKey": false,
          "notNull": true
        },
        "updated_at": {
          "default": "CURRENT_TIMESTAMP",
          "autoincrement": false,
          "name": "updated_at",
          "type": "timestamp",
          "primaryKey": false,
          "notNull": true,
          "onUpdate": true
        }
      },
      "compositePrimaryKeys": {
        "documents_doc_id": {
          "name": "documents_doc_id",
          "columns": [
            "doc_id"
          ]
        }
      },
      "indexes": {},
      "uniqueConstraints": {}
    },
    "leads": {
      "name": "leads",
      "columns": {
        "lead_id": {
          "autoincrement": true,
          "name": "lead_id",
          "type": "bigint",
          "primaryKey": false,
          "notNull": true
        },
        "contact_id": {
          "autoincrement": false,
          "name": "contact_id",
          "type": "bigint",
          "primaryKey": false,
          "notNull": true
        },
        "listing_id": {
          "autoincrement": false,
          "name": "listing_id",
          "type": "bigint",
          "primaryKey": false,
          "notNull": false
        },
        "source": {
          "autoincrement": false,
          "name": "source",
          "type": "varchar(50)",
          "primaryKey": false,
          "notNull": true
        },
        "status": {
          "autoincrement": false,
          "name": "status",
          "type": "varchar(20)",
          "primaryKey": false,
          "notNull": true
        },
        "created_at": {
          "default": "CURRENT_TIMESTAMP",
          "autoincrement": false,
          "name": "created_at",
          "type": "timestamp",
          "primaryKey": false,
          "notNull": true
        },
        "updated_at": {
          "default": "CURRENT_TIMESTAMP",
          "autoincrement": false,
          "name": "updated_at",
          "type": "timestamp",
          "primaryKey": false,
          "notNull": true,
          "onUpdate": true
        }
      },
      "compositePrimaryKeys": {
        "leads_lead_id": {
          "name": "leads_lead_id",
          "columns": [
            "lead_id"
          ]
        }
      },
      "indexes": {},
      "uniqueConstraints": {}
    },
    "listing_contacts": {
      "name": "listing_contacts",
      "columns": {
        "listing_contact_id": {
          "autoincrement": true,
          "name": "listing_contact_id",
          "type": "bigint",
          "primaryKey": false,
          "notNull": true
        },
        "listing_id": {
          "autoincrement": false,
          "name": "listing_id",
          "type": "bigint",
          "primaryKey": false,
          "notNull": true
        },
        "contact_id": {
          "autoincrement": false,
          "name": "contact_id",
          "type": "bigint",
          "primaryKey": false,
          "notNull": true
        },
        "contact_type": {
          "autoincrement": false,
          "name": "contact_type",
          "type": "varchar(20)",
          "primaryKey": false,
          "notNull": true
        },
        "created_at": {
          "default": "CURRENT_TIMESTAMP",
          "autoincrement": false,
          "name": "created_at",
          "type": "timestamp",
          "primaryKey": false,
          "notNull": true
        },
        "updated_at": {
          "default": "CURRENT_TIMESTAMP",
          "autoincrement": false,
          "name": "updated_at",
          "type": "timestamp",
          "primaryKey": false,
          "notNull": true,
          "onUpdate": true
        },
        "is_active": {
          "default": 1,
          "autoincrement": false,
          "name": "is_active",
          "type": "tinyint",
          "primaryKey": false,
          "notNull": false
        }
      },
      "compositePrimaryKeys": {
        "listing_contacts_listing_contact_id": {
          "name": "listing_contacts_listing_contact_id",
          "columns": [
            "listing_contact_id"
          ]
        }
      },
      "indexes": {},
      "uniqueConstraints": {}
    },
    "listings": {
      "name": "listings",
      "columns": {
        "listing_id": {
          "autoincrement": true,
          "name": "listing_id",
          "type": "bigint",
          "primaryKey": false,
          "notNull": true
        },
        "account_id": {
          "autoincrement": false,
          "name": "account_id",
          "type": "bigint",
          "primaryKey": false,
          "notNull": true
        },
        "property_id": {
          "autoincrement": false,
          "name": "property_id",
          "type": "bigint",
          "primaryKey": false,
          "notNull": true
        },
        "agent_id": {
          "autoincrement": false,
          "name": "agent_id",
          "type": "bigint",
          "primaryKey": false,
          "notNull": true
        },
        "listing_type": {
          "autoincrement": false,
          "name": "listing_type",
          "type": "varchar(20)",
          "primaryKey": false,
          "notNull": true
        },
        "price": {
          "autoincrement": false,
          "name": "price",
          "type": "decimal(12,2)",
          "primaryKey": false,
          "notNull": true
        },
        "status": {
          "autoincrement": false,
          "name": "status",
          "type": "varchar(20)",
          "primaryKey": false,
          "notNull": true
        },
        "is_furnished": {
          "autoincrement": false,
          "name": "is_furnished",
          "type": "tinyint",
          "primaryKey": false,
          "notNull": false
        },
        "furniture_quality": {
          "autoincrement": false,
          "name": "furniture_quality",
          "type": "varchar(50)",
          "primaryKey": false,
          "notNull": false
        },
        "optional_garage": {
          "autoincrement": false,
          "name": "optional_garage",
          "type": "tinyint",
          "primaryKey": false,
          "notNull": false
        },
        "optional_garage_price": {
          "autoincrement": false,
          "name": "optional_garage_price",
          "type": "decimal(12,2)",
          "primaryKey": false,
          "notNull": false
        },
        "optional_storage_room": {
          "default": 0,
          "autoincrement": false,
          "name": "optional_storage_room",
          "type": "tinyint",
          "primaryKey": false,
          "notNull": true
        },
        "optional_storage_room_price": {
          "autoincrement": false,
          "name": "optional_storage_room_price",
          "type": "decimal(12,2)",
          "primaryKey": false,
          "notNull": false
        },
        "has_keys": {
          "default": 0,
          "autoincrement": false,
          "name": "has_keys",
          "type": "tinyint",
          "primaryKey": false,
          "notNull": true
        },
        "student_friendly": {
          "autoincrement": false,
          "name": "student_friendly",
          "type": "tinyint",
          "primaryKey": false,
          "notNull": false
        },
        "pets_allowed": {
          "autoincrement": false,
          "name": "pets_allowed",
          "type": "tinyint",
          "primaryKey": false,
          "notNull": false
        },
        "appliances_included": {
          "autoincrement": false,
          "name": "appliances_included",
          "type": "tinyint",
          "primaryKey": false,
          "notNull": false
        },
        "internet": {
          "default": 0,
          "autoincrement": false,
          "name": "internet",
          "type": "tinyint",
          "primaryKey": false,
          "notNull": false
        },
        "oven": {
          "default": 0,
          "autoincrement": false,
          "name": "oven",
          "type": "tinyint",
          "primaryKey": false,
          "notNull": false
        },
        "microwave": {
          "default": 0,
          "autoincrement": false,
          "name": "microwave",
          "type": "tinyint",
          "primaryKey": false,
          "notNull": false
        },
        "washing_machine": {
          "default": 0,
          "autoincrement": false,
          "name": "washing_machine",
          "type": "tinyint",
          "primaryKey": false,
          "notNull": false
        },
        "fridge": {
          "default": 0,
          "autoincrement": false,
          "name": "fridge",
          "type": "tinyint",
          "primaryKey": false,
          "notNull": false
        },
        "tv": {
          "default": 0,
          "autoincrement": false,
          "name": "tv",
          "type": "tinyint",
          "primaryKey": false,
          "notNull": false
        },
        "stoneware": {
          "default": 0,
          "autoincrement": false,
          "name": "stoneware",
          "type": "tinyint",
          "primaryKey": false,
          "notNull": false
        },
        "is_featured": {
          "default": 0,
          "autoincrement": false,
          "name": "is_featured",
          "type": "tinyint",
          "primaryKey": false,
          "notNull": false
        },
        "is_bank_owned": {
          "default": 0,
          "autoincrement": false,
          "name": "is_bank_owned",
          "type": "tinyint",
          "primaryKey": false,
          "notNull": false
        },
        "is_active": {
          "default": 1,
          "autoincrement": false,
          "name": "is_active",
          "type": "tinyint",
          "primaryKey": false,
          "notNull": false
        },
        "visibility_mode": {
          "default": 1,
          "autoincrement": false,
          "name": "visibility_mode",
          "type": "smallint",
          "primaryKey": false,
          "notNull": false
        },
        "view_count": {
          "default": 0,
          "autoincrement": false,
          "name": "view_count",
          "type": "int",
          "primaryKey": false,
          "notNull": false
        },
        "inquiry_count": {
          "default": 0,
          "autoincrement": false,
          "name": "inquiry_count",
          "type": "int",
          "primaryKey": false,
          "notNull": false
        },
        "fotocasa": {
          "default": 0,
          "autoincrement": false,
          "name": "fotocasa",
          "type": "tinyint",
          "primaryKey": false,
          "notNull": false
        },
        "idealista": {
          "default": 0,
          "autoincrement": false,
          "name": "idealista",
          "type": "tinyint",
          "primaryKey": false,
          "notNull": false
        },
        "habitaclia": {
          "default": 0,
          "autoincrement": false,
          "name": "habitaclia",
          "type": "tinyint",
          "primaryKey": false,
          "notNull": false
        },
        "pisoscom": {
          "default": 0,
          "autoincrement": false,
          "name": "pisoscom",
          "type": "tinyint",
          "primaryKey": false,
          "notNull": false
        },
        "yaencontre": {
          "default": 0,
          "autoincrement": false,
          "name": "yaencontre",
          "type": "tinyint",
          "primaryKey": false,
          "notNull": false
        },
        "milanuncios": {
          "default": 0,
          "autoincrement": false,
          "name": "milanuncios",
          "type": "tinyint",
          "primaryKey": false,
          "notNull": false
        },
        "created_at": {
          "default": "CURRENT_TIMESTAMP",
          "autoincrement": false,
          "name": "created_at",
          "type": "timestamp",
          "primaryKey": false,
          "notNull": true
        },
        "updated_at": {
          "default": "CURRENT_TIMESTAMP",
          "autoincrement": false,
          "name": "updated_at",
          "type": "timestamp",
          "primaryKey": false,
          "notNull": true,
          "onUpdate": true
        }
      },
      "compositePrimaryKeys": {
        "listings_listing_id": {
          "name": "listings_listing_id",
          "columns": [
            "listing_id"
          ]
        }
      },
      "indexes": {},
      "uniqueConstraints": {}
    },
    "locations": {
      "name": "locations",
      "columns": {
        "neighborhood_id": {
          "autoincrement": true,
          "name": "neighborhood_id",
          "type": "bigint",
          "primaryKey": false,
          "notNull": true
        },
        "city": {
          "autoincrement": false,
          "name": "city",
          "type": "varchar(100)",
          "primaryKey": false,
          "notNull": true
        },
        "province": {
          "autoincrement": false,
          "name": "province",
          "type": "varchar(100)",
          "primaryKey": false,
          "notNull": true
        },
        "municipality": {
          "autoincrement": false,
          "name": "municipality",
          "type": "varchar(100)",
          "primaryKey": false,
          "notNull": true
        },
        "neighborhood": {
          "autoincrement": false,
          "name": "neighborhood",
          "type": "varchar(100)",
          "primaryKey": false,
          "notNull": true
        },
        "created_at": {
          "default": "CURRENT_TIMESTAMP",
          "autoincrement": false,
          "name": "created_at",
          "type": "timestamp",
          "primaryKey": false,
          "notNull": true
        },
        "updated_at": {
          "default": "CURRENT_TIMESTAMP",
          "autoincrement": false,
          "name": "updated_at",
          "type": "timestamp",
          "primaryKey": false,
          "notNull": true,
          "onUpdate": true
        },
        "is_active": {
          "default": 1,
          "autoincrement": false,
          "name": "is_active",
          "type": "tinyint",
          "primaryKey": false,
          "notNull": false
        }
      },
      "compositePrimaryKeys": {
        "locations_neighborhood_id": {
          "name": "locations_neighborhood_id",
          "columns": [
            "neighborhood_id"
          ]
        }
      },
      "indexes": {},
      "uniqueConstraints": {}
    },
    "organizations": {
      "name": "organizations",
      "columns": {
        "org_id": {
          "autoincrement": true,
          "name": "org_id",
          "type": "bigint",
          "primaryKey": false,
          "notNull": true
        },
        "org_name": {
          "autoincrement": false,
          "name": "org_name",
          "type": "varchar(255)",
          "primaryKey": false,
          "notNull": true
        },
        "address": {
          "autoincrement": false,
          "name": "address",
          "type": "varchar(255)",
          "primaryKey": false,
          "notNull": false
        },
        "city": {
          "autoincrement": false,
          "name": "city",
          "type": "varchar(100)",
          "primaryKey": false,
          "notNull": false
        },
        "state": {
          "autoincrement": false,
          "name": "state",
          "type": "varchar(100)",
          "primaryKey": false,
          "notNull": false
        },
        "postal_code": {
          "autoincrement": false,
          "name": "postal_code",
          "type": "varchar(20)",
          "primaryKey": false,
          "notNull": false
        },
        "country": {
          "autoincrement": false,
          "name": "country",
          "type": "varchar(100)",
          "primaryKey": false,
          "notNull": false
        }
      },
      "compositePrimaryKeys": {
        "organizations_org_id": {
          "name": "organizations_org_id",
          "columns": [
            "org_id"
          ]
        }
      },
      "indexes": {},
      "uniqueConstraints": {}
    },
    "properties": {
      "name": "properties",
      "columns": {
        "property_id": {
          "autoincrement": true,
          "name": "property_id",
          "type": "bigint",
          "primaryKey": false,
          "notNull": true
        },
        "account_id": {
          "autoincrement": false,
          "name": "account_id",
          "type": "bigint",
          "primaryKey": false,
          "notNull": true
        },
        "reference_number": {
          "autoincrement": false,
          "name": "reference_number",
          "type": "varchar(32)",
          "primaryKey": false,
          "notNull": false
        },
        "title": {
          "autoincrement": false,
          "name": "title",
          "type": "varchar(255)",
          "primaryKey": false,
          "notNull": false
        },
        "description": {
          "autoincrement": false,
          "name": "description",
          "type": "text",
          "primaryKey": false,
          "notNull": false
        },
        "property_type": {
          "default": "'piso'",
          "autoincrement": false,
          "name": "property_type",
          "type": "varchar(20)",
          "primaryKey": false,
          "notNull": false
        },
        "property_subtype": {
          "autoincrement": false,
          "name": "property_subtype",
          "type": "varchar(50)",
          "primaryKey": false,
          "notNull": false
        },
        "form_position": {
          "default": 1,
          "autoincrement": false,
          "name": "form_position",
          "type": "int",
          "primaryKey": false,
          "notNull": true
        },
        "bedrooms": {
          "autoincrement": false,
          "name": "bedrooms",
          "type": "smallint",
          "primaryKey": false,
          "notNull": false
        },
        "bathrooms": {
          "autoincrement": false,
          "name": "bathrooms",
          "type": "decimal(3,1)",
          "primaryKey": false,
          "notNull": false
        },
        "square_meter": {
          "autoincrement": false,
          "name": "square_meter",
          "type": "int",
          "primaryKey": false,
          "notNull": false
        },
        "year_built": {
          "autoincrement": false,
          "name": "year_built",
          "type": "smallint",
          "primaryKey": false,
          "notNull": false
        },
        "cadastral_reference": {
          "autoincrement": false,
          "name": "cadastral_reference",
          "type": "varchar(255)",
          "primaryKey": false,
          "notNull": false
        },
        "built_surface_area": {
          "autoincrement": false,
          "name": "built_surface_area",
          "type": "decimal(10,2)",
          "primaryKey": false,
          "notNull": false
        },
        "conservation_status": {
          "default": 1,
          "autoincrement": false,
          "name": "conservation_status",
          "type": "smallint",
          "primaryKey": false,
          "notNull": false
        },
        "street": {
          "autoincrement": false,
          "name": "street",
          "type": "varchar(255)",
          "primaryKey": false,
          "notNull": false
        },
        "address_details": {
          "autoincrement": false,
          "name": "address_details",
          "type": "varchar(255)",
          "primaryKey": false,
          "notNull": false
        },
        "postal_code": {
          "autoincrement": false,
          "name": "postal_code",
          "type": "varchar(20)",
          "primaryKey": false,
          "notNull": false
        },
        "neighborhood_id": {
          "autoincrement": false,
          "name": "neighborhood_id",
          "type": "bigint",
          "primaryKey": false,
          "notNull": false
        },
        "latitude": {
          "autoincrement": false,
          "name": "latitude",
          "type": "decimal(10,8)",
          "primaryKey": false,
          "notNull": false
        },
        "longitude": {
          "autoincrement": false,
          "name": "longitude",
          "type": "decimal(11,8)",
          "primaryKey": false,
          "notNull": false
        },
        "energy_certification": {
          "autoincrement": false,
          "name": "energy_certification",
          "type": "text",
          "primaryKey": false,
          "notNull": false
        },
        "energy_certificate_status": {
          "autoincrement": false,
          "name": "energy_certificate_status",
          "type": "varchar(20)",
          "primaryKey": false,
          "notNull": false
        },
        "energy_consumption_scale": {
          "autoincrement": false,
          "name": "energy_consumption_scale",
          "type": "varchar(2)",
          "primaryKey": false,
          "notNull": false
        },
        "energy_consumption_value": {
          "autoincrement": false,
          "name": "energy_consumption_value",
          "type": "decimal(6,2)",
          "primaryKey": false,
          "notNull": false
        },
        "emissions_scale": {
          "autoincrement": false,
          "name": "emissions_scale",
          "type": "varchar(2)",
          "primaryKey": false,
          "notNull": false
        },
        "emissions_value": {
          "autoincrement": false,
          "name": "emissions_value",
          "type": "decimal(6,2)",
          "primaryKey": false,
          "notNull": false
        },
        "has_heating": {
          "default": 0,
          "autoincrement": false,
          "name": "has_heating",
          "type": "tinyint",
          "primaryKey": false,
          "notNull": false
        },
        "heating_type": {
          "autoincrement": false,
          "name": "heating_type",
          "type": "varchar(50)",
          "primaryKey": false,
          "notNull": false
        },
        "has_elevator": {
          "default": 0,
          "autoincrement": false,
          "name": "has_elevator",
          "type": "tinyint",
          "primaryKey": false,
          "notNull": false
        },
        "has_garage": {
          "default": 0,
          "autoincrement": false,
          "name": "has_garage",
          "type": "tinyint",
          "primaryKey": false,
          "notNull": false
        },
        "has_storage_room": {
          "default": 0,
          "autoincrement": false,
          "name": "has_storage_room",
          "type": "tinyint",
          "primaryKey": false,
          "notNull": false
        },
        "created_at": {
          "default": "CURRENT_TIMESTAMP",
          "autoincrement": false,
          "name": "created_at",
          "type": "timestamp",
          "primaryKey": false,
          "notNull": true
        },
        "updated_at": {
          "default": "CURRENT_TIMESTAMP",
          "autoincrement": false,
          "name": "updated_at",
          "type": "timestamp",
          "primaryKey": false,
          "notNull": true,
          "onUpdate": true
        },
        "is_active": {
          "default": 1,
          "autoincrement": false,
          "name": "is_active",
          "type": "tinyint",
          "primaryKey": false,
          "notNull": false
        },
        "garage_type": {
          "autoincrement": false,
          "name": "garage_type",
          "type": "varchar(50)",
          "primaryKey": false,
          "notNull": false
        },
        "garage_spaces": {
          "autoincrement": false,
          "name": "garage_spaces",
          "type": "smallint",
          "primaryKey": false,
          "notNull": false
        },
        "garage_in_building": {
          "autoincrement": false,
          "name": "garage_in_building",
          "type": "tinyint",
          "primaryKey": false,
          "notNull": false
        },
        "elevator_to_garage": {
          "autoincrement": false,
          "name": "elevator_to_garage",
          "type": "tinyint",
          "primaryKey": false,
          "notNull": false
        },
        "garage_number": {
          "autoincrement": false,
          "name": "garage_number",
          "type": "varchar(20)",
          "primaryKey": false,
          "notNull": false
        },
        "gym": {
          "default": 0,
          "autoincrement": false,
          "name": "gym",
          "type": "tinyint",
          "primaryKey": false,
          "notNull": false
        },
        "sports_area": {
          "default": 0,
          "autoincrement": false,
          "name": "sports_area",
          "type": "tinyint",
          "primaryKey": false,
          "notNull": false
        },
        "children_area": {
          "default": 0,
          "autoincrement": false,
          "name": "children_area",
          "type": "tinyint",
          "primaryKey": false,
          "notNull": false
        },
        "suite_bathroom": {
          "default": 0,
          "autoincrement": false,
          "name": "suite_bathroom",
          "type": "tinyint",
          "primaryKey": false,
          "notNull": false
        },
        "nearby_public_transport": {
          "default": 0,
          "autoincrement": false,
          "name": "nearby_public_transport",
          "type": "tinyint",
          "primaryKey": false,
          "notNull": false
        },
        "community_pool": {
          "default": 0,
          "autoincrement": false,
          "name": "community_pool",
          "type": "tinyint",
          "primaryKey": false,
          "notNull": false
        },
        "private_pool": {
          "default": 0,
          "autoincrement": false,
          "name": "private_pool",
          "type": "tinyint",
          "primaryKey": false,
          "notNull": false
        },
        "tennis_court": {
          "default": 0,
          "autoincrement": false,
          "name": "tennis_court",
          "type": "tinyint",
          "primaryKey": false,
          "notNull": false
        },
        "disabled_accessible": {
          "autoincrement": false,
          "name": "disabled_accessible",
          "type": "tinyint",
          "primaryKey": false,
          "notNull": false
        },
        "vpo": {
          "autoincrement": false,
          "name": "vpo",
          "type": "tinyint",
          "primaryKey": false,
          "notNull": false
        },
        "video_intercom": {
          "autoincrement": false,
          "name": "video_intercom",
          "type": "tinyint",
          "primaryKey": false,
          "notNull": false
        },
        "concierge_service": {
          "autoincrement": false,
          "name": "concierge_service",
          "type": "tinyint",
          "primaryKey": false,
          "notNull": false
        },
        "security_guard": {
          "autoincrement": false,
          "name": "security_guard",
          "type": "tinyint",
          "primaryKey": false,
          "notNull": false
        },
        "satellite_dish": {
          "autoincrement": false,
          "name": "satellite_dish",
          "type": "tinyint",
          "primaryKey": false,
          "notNull": false
        },
        "double_glazing": {
          "autoincrement": false,
          "name": "double_glazing",
          "type": "tinyint",
          "primaryKey": false,
          "notNull": false
        },
        "alarm": {
          "autoincrement": false,
          "name": "alarm",
          "type": "tinyint",
          "primaryKey": false,
          "notNull": false
        },
        "security_door": {
          "autoincrement": false,
          "name": "security_door",
          "type": "tinyint",
          "primaryKey": false,
          "notNull": false
        },
        "brand_new": {
          "autoincrement": false,
          "name": "brand_new",
          "type": "tinyint",
          "primaryKey": false,
          "notNull": false
        },
        "new_construction": {
          "autoincrement": false,
          "name": "new_construction",
          "type": "tinyint",
          "primaryKey": false,
          "notNull": false
        },
        "under_construction": {
          "autoincrement": false,
          "name": "under_construction",
          "type": "tinyint",
          "primaryKey": false,
          "notNull": false
        },
        "needs_renovation": {
          "autoincrement": false,
          "name": "needs_renovation",
          "type": "tinyint",
          "primaryKey": false,
          "notNull": false
        },
        "last_renovation_year": {
          "autoincrement": false,
          "name": "last_renovation_year",
          "type": "smallint",
          "primaryKey": false,
          "notNull": false
        },
        "kitchen_type": {
          "autoincrement": false,
          "name": "kitchen_type",
          "type": "varchar(50)",
          "primaryKey": false,
          "notNull": false
        },
        "hot_water_type": {
          "autoincrement": false,
          "name": "hot_water_type",
          "type": "varchar(50)",
          "primaryKey": false,
          "notNull": false
        },
        "open_kitchen": {
          "autoincrement": false,
          "name": "open_kitchen",
          "type": "tinyint",
          "primaryKey": false,
          "notNull": false
        },
        "french_kitchen": {
          "autoincrement": false,
          "name": "french_kitchen",
          "type": "tinyint",
          "primaryKey": false,
          "notNull": false
        },
        "furnished_kitchen": {
          "autoincrement": false,
          "name": "furnished_kitchen",
          "type": "tinyint",
          "primaryKey": false,
          "notNull": false
        },
        "pantry": {
          "autoincrement": false,
          "name": "pantry",
          "type": "tinyint",
          "primaryKey": false,
          "notNull": false
        },
        "storage_room_size": {
          "autoincrement": false,
          "name": "storage_room_size",
          "type": "int",
          "primaryKey": false,
          "notNull": false
        },
        "storage_room_number": {
          "autoincrement": false,
          "name": "storage_room_number",
          "type": "varchar(20)",
          "primaryKey": false,
          "notNull": false
        },
        "terrace": {
          "autoincrement": false,
          "name": "terrace",
          "type": "tinyint",
          "primaryKey": false,
          "notNull": false
        },
        "terrace_size": {
          "autoincrement": false,
          "name": "terrace_size",
          "type": "int",
          "primaryKey": false,
          "notNull": false
        },
        "wine_cellar": {
          "autoincrement": false,
          "name": "wine_cellar",
          "type": "tinyint",
          "primaryKey": false,
          "notNull": false
        },
        "wine_cellar_size": {
          "autoincrement": false,
          "name": "wine_cellar_size",
          "type": "int",
          "primaryKey": false,
          "notNull": false
        },
        "living_room_size": {
          "autoincrement": false,
          "name": "living_room_size",
          "type": "int",
          "primaryKey": false,
          "notNull": false
        },
        "balcony_count": {
          "autoincrement": false,
          "name": "balcony_count",
          "type": "smallint",
          "primaryKey": false,
          "notNull": false
        },
        "gallery_count": {
          "autoincrement": false,
          "name": "gallery_count",
          "type": "smallint",
          "primaryKey": false,
          "notNull": false
        },
        "building_floors": {
          "autoincrement": false,
          "name": "building_floors",
          "type": "smallint",
          "primaryKey": false,
          "notNull": false
        },
        "built_in_wardrobes": {
          "autoincrement": false,
          "name": "built_in_wardrobes",
          "type": "varchar(50)",
          "primaryKey": false,
          "notNull": false
        },
        "main_floor_type": {
          "autoincrement": false,
          "name": "main_floor_type",
          "type": "varchar(50)",
          "primaryKey": false,
          "notNull": false
        },
        "shutter_type": {
          "autoincrement": false,
          "name": "shutter_type",
          "type": "varchar(50)",
          "primaryKey": false,
          "notNull": false
        },
        "carpentry_type": {
          "autoincrement": false,
          "name": "carpentry_type",
          "type": "varchar(50)",
          "primaryKey": false,
          "notNull": false
        },
        "orientation": {
          "autoincrement": false,
          "name": "orientation",
          "type": "varchar(50)",
          "primaryKey": false,
          "notNull": false
        },
        "air_conditioning_type": {
          "autoincrement": false,
          "name": "air_conditioning_type",
          "type": "varchar(50)",
          "primaryKey": false,
          "notNull": false
        },
        "window_type": {
          "autoincrement": false,
          "name": "window_type",
          "type": "varchar(50)",
          "primaryKey": false,
          "notNull": false
        },
        "exterior": {
          "autoincrement": false,
          "name": "exterior",
          "type": "tinyint",
          "primaryKey": false,
          "notNull": false
        },
        "bright": {
          "autoincrement": false,
          "name": "bright",
          "type": "tinyint",
          "primaryKey": false,
          "notNull": false
        },
        "views": {
          "autoincrement": false,
          "name": "views",
          "type": "tinyint",
          "primaryKey": false,
          "notNull": false
        },
        "mountain_views": {
          "autoincrement": false,
          "name": "mountain_views",
          "type": "tinyint",
          "primaryKey": false,
          "notNull": false
        },
        "sea_views": {
          "autoincrement": false,
          "name": "sea_views",
          "type": "tinyint",
          "primaryKey": false,
          "notNull": false
        },
        "beachfront": {
          "autoincrement": false,
          "name": "beachfront",
          "type": "tinyint",
          "primaryKey": false,
          "notNull": false
        },
        "jacuzzi": {
          "autoincrement": false,
          "name": "jacuzzi",
          "type": "tinyint",
          "primaryKey": false,
          "notNull": false
        },
        "hydromassage": {
          "autoincrement": false,
          "name": "hydromassage",
          "type": "tinyint",
          "primaryKey": false,
          "notNull": false
        },
        "garden": {
          "autoincrement": false,
          "name": "garden",
          "type": "tinyint",
          "primaryKey": false,
          "notNull": false
        },
        "pool": {
          "autoincrement": false,
          "name": "pool",
          "type": "tinyint",
          "primaryKey": false,
          "notNull": false
        },
        "home_automation": {
          "autoincrement": false,
          "name": "home_automation",
          "type": "tinyint",
          "primaryKey": false,
          "notNull": false
        },
        "music_system": {
          "autoincrement": false,
          "name": "music_system",
          "type": "tinyint",
          "primaryKey": false,
          "notNull": false
        },
        "laundry_room": {
          "autoincrement": false,
          "name": "laundry_room",
          "type": "tinyint",
          "primaryKey": false,
          "notNull": false
        },
        "covered_clothesline": {
          "autoincrement": false,
          "name": "covered_clothesline",
          "type": "tinyint",
          "primaryKey": false,
          "notNull": false
        },
        "fireplace": {
          "autoincrement": false,
          "name": "fireplace",
          "type": "tinyint",
          "primaryKey": false,
          "notNull": false
        }
      },
      "compositePrimaryKeys": {
        "properties_property_id": {
          "name": "properties_property_id",
          "columns": [
            "property_id"
          ]
        }
      },
      "indexes": {},
      "uniqueConstraints": {}
    },
    "property_images": {
      "name": "property_images",
      "columns": {
        "property_image_id": {
          "autoincrement": true,
          "name": "property_image_id",
          "type": "bigint",
          "primaryKey": false,
          "notNull": true
        },
        "property_id": {
          "autoincrement": false,
          "name": "property_id",
          "type": "bigint",
          "primaryKey": false,
          "notNull": true
        },
        "reference_number": {
          "autoincrement": false,
          "name": "reference_number",
          "type": "varchar(32)",
          "primaryKey": false,
          "notNull": true
        },
        "image_url": {
          "autoincrement": false,
          "name": "image_url",
          "type": "varchar(255)",
          "primaryKey": false,
          "notNull": true
        },
        "is_active": {
          "default": 1,
          "autoincrement": false,
          "name": "is_active",
          "type": "tinyint",
          "primaryKey": false,
          "notNull": false
        },
        "created_at": {
          "default": "CURRENT_TIMESTAMP",
          "autoincrement": false,
          "name": "created_at",
          "type": "timestamp",
          "primaryKey": false,
          "notNull": true
        },
        "updated_at": {
          "default": "CURRENT_TIMESTAMP",
          "autoincrement": false,
          "name": "updated_at",
          "type": "timestamp",
          "primaryKey": false,
          "notNull": true,
          "onUpdate": true
        },
        "image_key": {
          "autoincrement": false,
          "name": "image_key",
          "type": "varchar(2048)",
          "primaryKey": false,
          "notNull": true
        },
        "image_tag": {
          "autoincrement": false,
          "name": "image_tag",
          "type": "varchar(255)",
          "primaryKey": false,
          "notNull": false
        },
        "s3key": {
          "autoincrement": false,
          "name": "s3key",
          "type": "varchar(2048)",
          "primaryKey": false,
          "notNull": true
        },
        "image_order": {
          "default": 0,
          "autoincrement": false,
          "name": "image_order",
          "type": "int",
          "primaryKey": false,
          "notNull": true
        }
      },
      "compositePrimaryKeys": {
        "property_images_property_image_id": {
          "name": "property_images_property_image_id",
          "columns": [
            "property_image_id"
          ]
        }
      },
      "indexes": {},
      "uniqueConstraints": {}
    },
    "prospect_history": {
      "name": "prospect_history",
      "columns": {
        "history_id": {
          "autoincrement": true,
          "name": "history_id",
          "type": "bigint",
          "primaryKey": false,
          "notNull": true
        },
        "prospect_id": {
          "autoincrement": false,
          "name": "prospect_id",
          "type": "bigint",
          "primaryKey": false,
          "notNull": true
        },
        "previous_status": {
          "autoincrement": false,
          "name": "previous_status",
          "type": "varchar(50)",
          "primaryKey": false,
          "notNull": false
        },
        "new_status": {
          "autoincrement": false,
          "name": "new_status",
          "type": "varchar(50)",
          "primaryKey": false,
          "notNull": true
        },
        "changed_by": {
          "autoincrement": false,
          "name": "changed_by",
          "type": "varchar(36)",
          "primaryKey": false,
          "notNull": true
        },
        "change_reason": {
          "autoincrement": false,
          "name": "change_reason",
          "type": "text",
          "primaryKey": false,
          "notNull": false
        },
        "created_at": {
          "default": "CURRENT_TIMESTAMP",
          "autoincrement": false,
          "name": "created_at",
          "type": "timestamp",
          "primaryKey": false,
          "notNull": true
        }
      },
      "compositePrimaryKeys": {
        "prospect_history_history_id": {
          "name": "prospect_history_history_id",
          "columns": [
            "history_id"
          ]
        }
      },
      "indexes": {},
      "uniqueConstraints": {}
    },
    "prospects": {
      "name": "prospects",
      "columns": {
        "prospect_id": {
          "autoincrement": true,
          "name": "prospect_id",
          "type": "bigint",
          "primaryKey": false,
          "notNull": true
        },
        "contact_id": {
          "autoincrement": false,
          "name": "contact_id",
          "type": "bigint",
          "primaryKey": false,
          "notNull": true
        },
        "status": {
          "autoincrement": false,
          "name": "status",
          "type": "varchar(50)",
          "primaryKey": false,
          "notNull": true
        },
        "listing_type": {
          "autoincrement": false,
          "name": "listing_type",
          "type": "varchar(20)",
          "primaryKey": false,
          "notNull": false
        },
        "property_type": {
          "autoincrement": false,
          "name": "property_type",
          "type": "varchar(20)",
          "primaryKey": false,
          "notNull": false
        },
        "min_price": {
          "autoincrement": false,
          "name": "min_price",
          "type": "decimal(12,2)",
          "primaryKey": false,
          "notNull": false
        },
        "max_price": {
          "autoincrement": false,
          "name": "max_price",
          "type": "decimal(12,2)",
          "primaryKey": false,
          "notNull": false
        },
        "preferred_areas": {
          "autoincrement": false,
          "name": "preferred_areas",
          "type": "JSON",
          "primaryKey": false,
          "notNull": false
        },
        "min_bedrooms": {
          "autoincrement": false,
          "name": "min_bedrooms",
          "type": "smallint",
          "primaryKey": false,
          "notNull": false
        },
        "min_bathrooms": {
          "autoincrement": false,
          "name": "min_bathrooms",
          "type": "smallint",
          "primaryKey": false,
          "notNull": false
        },
        "min_square_meters": {
          "autoincrement": false,
          "name": "min_square_meters",
          "type": "int",
          "primaryKey": false,
          "notNull": false
        },
        "max_square_meters": {
          "autoincrement": false,
          "name": "max_square_meters",
          "type": "int",
          "primaryKey": false,
          "notNull": false
        },
        "move_in_by": {
          "autoincrement": false,
          "name": "move_in_by",
          "type": "timestamp",
          "primaryKey": false,
          "notNull": false
        },
        "extras": {
          "autoincrement": false,
          "name": "extras",
          "type": "JSON",
          "primaryKey": false,
          "notNull": false
        },
        "urgency_level": {
          "autoincrement": false,
          "name": "urgency_level",
          "type": "smallint",
          "primaryKey": false,
          "notNull": false
        },
        "funding_ready": {
          "autoincrement": false,
          "name": "funding_ready",
          "type": "tinyint",
          "primaryKey": false,
          "notNull": false
        },
        "notes_internal": {
          "autoincrement": false,
          "name": "notes_internal",
          "type": "text",
          "primaryKey": false,
          "notNull": false
        },
        "created_at": {
          "default": "CURRENT_TIMESTAMP",
          "autoincrement": false,
          "name": "created_at",
          "type": "timestamp",
          "primaryKey": false,
          "notNull": true
        },
        "updated_at": {
          "default": "CURRENT_TIMESTAMP",
          "autoincrement": false,
          "name": "updated_at",
          "type": "timestamp",
          "primaryKey": false,
          "notNull": true,
          "onUpdate": true
        }
      },
      "compositePrimaryKeys": {
        "prospects_prospect_id": {
          "name": "prospects_prospect_id",
          "columns": [
            "prospect_id"
          ]
        }
      },
      "indexes": {},
      "uniqueConstraints": {}
    },
    "roles": {
      "name": "roles",
      "columns": {
        "role_id": {
          "autoincrement": true,
          "name": "role_id",
          "type": "bigint",
          "primaryKey": false,
          "notNull": true
        },
        "name": {
          "autoincrement": false,
          "name": "name",
          "type": "varchar(50)",
          "primaryKey": false,
          "notNull": true
        },
        "description": {
          "autoincrement": false,
          "name": "description",
          "type": "varchar(255)",
          "primaryKey": false,
          "notNull": false
        },
        "permissions": {
          "default": "'{}'",
          "autoincrement": false,
          "name": "permissions",
          "type": "JSON",
          "primaryKey": false,
          "notNull": false
        },
        "created_at": {
          "default": "CURRENT_TIMESTAMP",
          "autoincrement": false,
          "name": "created_at",
          "type": "timestamp",
          "primaryKey": false,
          "notNull": true
        },
        "updated_at": {
          "default": "CURRENT_TIMESTAMP",
          "autoincrement": false,
          "name": "updated_at",
          "type": "timestamp",
          "primaryKey": false,
          "notNull": true,
          "onUpdate": true
        },
        "is_active": {
          "default": 1,
          "autoincrement": false,
          "name": "is_active",
          "type": "tinyint",
          "primaryKey": false,
          "notNull": false
        }
      },
      "compositePrimaryKeys": {
        "roles_role_id": {
          "name": "roles_role_id",
          "columns": [
            "role_id"
          ]
        }
      },
      "indexes": {},
      "uniqueConstraints": {}
    },
    "sessions": {
      "name": "sessions",
      "columns": {
        "id": {
          "autoincrement": false,
          "name": "id",
          "type": "varchar(36)",
          "primaryKey": false,
          "notNull": true
        },
        "expires_at": {
          "autoincrement": false,
          "name": "expires_at",
          "type": "timestamp",
          "primaryKey": false,
          "notNull": true
        },
        "token": {
          "autoincrement": false,
          "name": "token",
          "type": "varchar(255)",
          "primaryKey": false,
          "notNull": true
        },
        "created_at": {
          "default": "CURRENT_TIMESTAMP",
          "autoincrement": false,
          "name": "created_at",
          "type": "timestamp",
          "primaryKey": false,
          "notNull": true
        },
        "updated_at": {
          "default": "CURRENT_TIMESTAMP",
          "autoincrement": false,
          "name": "updated_at",
          "type": "timestamp",
          "primaryKey": false,
          "notNull": true,
          "onUpdate": true
        },
        "ip_address": {
          "autoincrement": false,
          "name": "ip_address",
          "type": "text",
          "primaryKey": false,
          "notNull": false
        },
        "user_agent": {
          "autoincrement": false,
          "name": "user_agent",
          "type": "text",
          "primaryKey": false,
          "notNull": false
        },
        "user_id": {
          "autoincrement": false,
          "name": "user_id",
          "type": "varchar(36)",
          "primaryKey": false,
          "notNull": true
        }
      },
      "compositePrimaryKeys": {
        "sessions_id": {
          "name": "sessions_id",
          "columns": [
            "id"
          ]
        }
      },
      "indexes": {},
      "uniqueConstraints": {}
    },
    "tasks": {
      "name": "tasks",
      "columns": {
        "task_id": {
          "autoincrement": true,
          "name": "task_id",
          "type": "bigint",
          "primaryKey": false,
          "notNull": true
        },
        "user_id": {
          "autoincrement": false,
          "name": "user_id",
          "type": "varchar(36)",
          "primaryKey": false,
          "notNull": true
        },
        "description": {
          "autoincrement": false,
          "name": "description",
          "type": "text",
          "primaryKey": false,
          "notNull": true
        },
        "due_date": {
          "autoincrement": false,
          "name": "due_date",
          "type": "timestamp",
          "primaryKey": false,
          "notNull": false
        },
        "completed": {
          "default": 0,
          "autoincrement": false,
          "name": "completed",
          "type": "tinyint",
          "primaryKey": false,
          "notNull": false
        },
        "listing_id": {
          "autoincrement": false,
          "name": "listing_id",
          "type": "bigint",
          "primaryKey": false,
          "notNull": false
        },
        "lead_id": {
          "autoincrement": false,
          "name": "lead_id",
          "type": "bigint",
          "primaryKey": false,
          "notNull": false
        },
        "deal_id": {
          "autoincrement": false,
          "name": "deal_id",
          "type": "bigint",
          "primaryKey": false,
          "notNull": false
        },
        "appointment_id": {
          "autoincrement": false,
          "name": "appointment_id",
          "type": "bigint",
          "primaryKey": false,
          "notNull": false
        },
        "prospect_id": {
          "autoincrement": false,
          "name": "prospect_id",
          "type": "bigint",
          "primaryKey": false,
          "notNull": false
        },
        "is_active": {
          "default": 1,
          "autoincrement": false,
          "name": "is_active",
          "type": "tinyint",
          "primaryKey": false,
          "notNull": false
        },
        "created_at": {
          "default": "CURRENT_TIMESTAMP",
          "autoincrement": false,
          "name": "created_at",
          "type": "timestamp",
          "primaryKey": false,
          "notNull": true
        },
        "updated_at": {
          "default": "CURRENT_TIMESTAMP",
          "autoincrement": false,
          "name": "updated_at",
          "type": "timestamp",
          "primaryKey": false,
          "notNull": true,
          "onUpdate": true
        }
      },
      "compositePrimaryKeys": {
        "tasks_task_id": {
          "name": "tasks_task_id",
          "columns": [
            "task_id"
          ]
        }
      },
      "indexes": {},
      "uniqueConstraints": {}
    },
    "user_roles": {
      "name": "user_roles",
      "columns": {
        "user_role_id": {
          "autoincrement": true,
          "name": "user_role_id",
          "type": "bigint",
          "primaryKey": false,
          "notNull": true
        },
        "user_id": {
          "autoincrement": false,
          "name": "user_id",
          "type": "varchar(36)",
          "primaryKey": false,
          "notNull": true
        },
        "role_id": {
          "autoincrement": false,
          "name": "role_id",
          "type": "bigint",
          "primaryKey": false,
          "notNull": true
        },
        "created_at": {
          "default": "CURRENT_TIMESTAMP",
          "autoincrement": false,
          "name": "created_at",
          "type": "timestamp",
          "primaryKey": false,
          "notNull": true
        },
        "updated_at": {
          "default": "CURRENT_TIMESTAMP",
          "autoincrement": false,
          "name": "updated_at",
          "type": "timestamp",
          "primaryKey": false,
          "notNull": true,
          "onUpdate": true
        },
        "is_active": {
          "default": 1,
          "autoincrement": false,
          "name": "is_active",
          "type": "tinyint",
          "primaryKey": false,
          "notNull": false
        }
      },
      "compositePrimaryKeys": {
        "user_roles_user_role_id": {
          "name": "user_roles_user_role_id",
          "columns": [
            "user_role_id"
          ]
        }
      },
      "indexes": {},
      "uniqueConstraints": {}
    },
    "users": {
      "name": "users",
      "columns": {
        "id": {
          "autoincrement": false,
          "name": "id",
          "type": "varchar(36)",
          "primaryKey": false,
          "notNull": true
        },
        "name": {
          "autoincrement": false,
          "name": "name",
          "type": "varchar(200)",
          "primaryKey": false,
          "notNull": true
        },
        "email": {
          "autoincrement": false,
          "name": "email",
          "type": "varchar(255)",
          "primaryKey": false,
          "notNull": true
        },
        "email_verified": {
          "default": 0,
          "autoincrement": false,
          "name": "email_verified",
          "type": "tinyint",
          "primaryKey": false,
          "notNull": false
        },
        "email_verified_at": {
          "autoincrement": false,
          "name": "email_verified_at",
          "type": "timestamp",
          "primaryKey": false,
          "notNull": false
        },
        "image": {
          "autoincrement": false,
          "name": "image",
          "type": "varchar(255)",
          "primaryKey": false,
          "notNull": false
        },
        "created_at": {
          "default": "CURRENT_TIMESTAMP",
          "autoincrement": false,
          "name": "created_at",
          "type": "timestamp",
          "primaryKey": false,
          "notNull": true
        },
        "updated_at": {
          "default": "CURRENT_TIMESTAMP",
          "autoincrement": false,
          "name": "updated_at",
          "type": "timestamp",
          "primaryKey": false,
          "notNull": true,
          "onUpdate": true
        },
        "password": {
          "autoincrement": false,
          "name": "password",
          "type": "varchar(255)",
          "primaryKey": false,
          "notNull": false
        },
        "account_id": {
          "autoincrement": false,
          "name": "account_id",
          "type": "bigint",
          "primaryKey": false,
          "notNull": true
        },
        "first_name": {
          "autoincrement": false,
          "name": "first_name",
          "type": "varchar(100)",
          "primaryKey": false,
          "notNull": true
        },
        "last_name": {
          "autoincrement": false,
          "name": "last_name",
          "type": "varchar(100)",
          "primaryKey": false,
          "notNull": true
        },
        "phone": {
          "autoincrement": false,
          "name": "phone",
          "type": "varchar(20)",
          "primaryKey": false,
          "notNull": false
        },
        "timezone": {
          "default": "'UTC'",
          "autoincrement": false,
          "name": "timezone",
          "type": "varchar(50)",
          "primaryKey": false,
          "notNull": false
        },
        "language": {
          "default": "'en'",
          "autoincrement": false,
          "name": "language",
          "type": "varchar(10)",
          "primaryKey": false,
          "notNull": false
        },
        "preferences": {
          "default": "'{}'",
          "autoincrement": false,
          "name": "preferences",
          "type": "JSON",
          "primaryKey": false,
          "notNull": false
        },
        "last_login": {
          "autoincrement": false,
          "name": "last_login",
          "type": "timestamp",
          "primaryKey": false,
          "notNull": false
        },
        "is_verified": {
          "default": 0,
          "autoincrement": false,
          "name": "is_verified",
          "type": "tinyint",
          "primaryKey": false,
          "notNull": false
        },
        "is_active": {
          "default": 1,
          "autoincrement": false,
          "name": "is_active",
          "type": "tinyint",
          "primaryKey": false,
          "notNull": false
        }
      },
      "compositePrimaryKeys": {
        "users_id": {
          "name": "users_id",
          "columns": [
            "id"
          ]
        }
      },
      "indexes": {},
      "uniqueConstraints": {}
    },
    "verification_tokens": {
      "name": "verification_tokens",
      "columns": {
        "id": {
          "autoincrement": false,
          "name": "id",
          "type": "varchar(36)",
          "primaryKey": false,
          "notNull": true
        },
        "identifier": {
          "autoincrement": false,
          "name": "identifier",
          "type": "text",
          "primaryKey": false,
          "notNull": true
        },
        "value": {
          "autoincrement": false,
          "name": "value",
          "type": "text",
          "primaryKey": false,
          "notNull": true
        },
        "expires_at": {
          "autoincrement": false,
          "name": "expires_at",
          "type": "timestamp",
          "primaryKey": false,
          "notNull": true
        },
        "created_at": {
          "default": "CURRENT_TIMESTAMP",
          "autoincrement": false,
          "name": "created_at",
          "type": "timestamp",
          "primaryKey": false,
          "notNull": true
        },
        "updated_at": {
          "default": "CURRENT_TIMESTAMP",
          "autoincrement": false,
          "name": "updated_at",
          "type": "timestamp",
          "primaryKey": false,
          "notNull": true,
          "onUpdate": true
        }
      },
      "compositePrimaryKeys": {
        "verification_tokens_id": {
          "name": "verification_tokens_id",
          "columns": [
            "id"
          ]
        }
      },
      "indexes": {},
      "uniqueConstraints": {}
    }
  },
  "_meta": {
    "schemas": {},
    "tables": {},
    "columns": {}
  },
  "internal": {
    "tables": {},
    "indexes": {}
  }
}